contextooor/.env.example
contextooor/.gitignore
contextooor/__init__.py
contextooor/btc.py
contextooor/chainalysis_ofac_api.py
contextooor_btc-0.9.9.92.dist-info/WHEEL
contextooor_btc-0.9.9.92.dist-info/METADATA
contextooor_btc-0.9.9.92.dist-info/RECORD
